phomo/__init__.py
phomo/__main__.py
phomo/grid.py
phomo/master.py
phomo/metrics.py
phomo/mosaic.py
phomo/palette.py
phomo/pool.py
phomo/utils.py
phomo-1.2.0.dist-info/LICENSE
phomo-1.2.0.dist-info/METADATA
phomo-1.2.0.dist-info/WHEEL
phomo-1.2.0.dist-info/entry_points.txt
phomo-1.2.0.dist-info/RECORD
