Metadata-Version: 2.1
Name: phomo
Version: 1.2.0
Summary: Python package and CLI utility to create photo mosaics.
Home-page: https://github.com/loiccoyle/phomo
License: MIT
Keywords: photomosaic,photographic,mosaic,art,image
Author: Loic Coyle
Author-email: loic.coyle@hotmail.fr
Requires-Python: >=3.9,<3.13
Classifier: License :: OSI Approved :: MIT License
Classifier: Operating System :: MacOS
Classifier: Operating System :: Microsoft :: Windows
Classifier: Operating System :: POSIX :: Linux
Classifier: Programming Language :: Python :: 3
Classifier: Programming Language :: Python :: 3.9
Classifier: Programming Language :: Python :: 3.10
Classifier: Programming Language :: Python :: 3.11
Classifier: Programming Language :: Python :: 3.12
Classifier: Programming Language :: Python :: 3 :: Only
Classifier: Topic :: Artistic Software
Classifier: Topic :: Scientific/Engineering :: Image Processing
Classifier: Topic :: Software Development :: Libraries :: Python Modules
Provides-Extra: cuda
Requires-Dist: matplotlib (>=3.4.1,<4.0.0)
Requires-Dist: numba (>=0.60.0,<0.61.0) ; extra == "cuda"
Requires-Dist: numpy (>=2.0.0,<3.0.0)
Requires-Dist: opencv-python (>=4.10.0.84,<5.0.0.0)
Requires-Dist: pillow (>=10.0.1,<11.0.0)
Requires-Dist: scipy (>=1.11.2,<2.0.0)
Requires-Dist: tqdm (>=4.60.0,<5.0.0)
Project-URL: Repository, https://github.com/loiccoyle/phomo
